pylinkvalidator/__init__.py
pylinkvalidator/api.py
pylinkvalidator/compat.py
pylinkvalidator/crawler.py
pylinkvalidator/models.py
pylinkvalidator/reporter.py
pylinkvalidator/tests.py
pylinkvalidator/urlutil.py
pylinkvalidator/bs4/__init__.py
pylinkvalidator/bs4/dammit.py
pylinkvalidator/bs4/diagnose.py
pylinkvalidator/bs4/element.py
pylinkvalidator/bs4/builder/__init__.py
pylinkvalidator/bs4/builder/_html5lib.py
pylinkvalidator/bs4/builder/_htmlparser.py
pylinkvalidator/bs4/builder/_lxml.py
pylinkvalidator-0.3.data/scripts/pylinkvalidate.py
pylinkvalidator-0.3.dist-info/DESCRIPTION.rst
pylinkvalidator-0.3.dist-info/METADATA
pylinkvalidator-0.3.dist-info/metadata.json
pylinkvalidator-0.3.dist-info/RECORD
pylinkvalidator-0.3.dist-info/top_level.txt
pylinkvalidator-0.3.dist-info/WHEEL
