Metadata-Version: 2.0
Name: pylinkvalidator
Version: 0.3
Summary: Simple crawler that detects link errors such as 404 and 500.
Home-page: https://github.com/bartdag/pylinkvalidator
Author: Barthelemy Dagenais
Author-email: barthelemy@infobart.com
License: BSD License
Platform: UNKNOWN
Classifier: Environment :: Console
Classifier: Intended Audience :: Developers
Classifier: License :: OSI Approved :: BSD License
Classifier: Operating System :: OS Independent
Classifier: Programming Language :: Python
Classifier: Programming Language :: Python :: 2
Classifier: Programming Language :: Python :: 2.6
Classifier: Programming Language :: Python :: 2.7
Classifier: Programming Language :: Python :: 3
Classifier: Programming Language :: Python :: 3.3
Classifier: Topic :: Internet :: WWW/HTTP :: Site Management :: Link Checking
Classifier: Topic :: Utilities
